{
  "active": true,
  "connections": {
    "Webhook": {
      "main": [
        [
          {
            "node": "Split Out",
            "type": "main",
            "index": 0
          }
        ]
      ]
    },
    "Split Out": {
      "main": [
        [
          {
            "node": "Filter",
            "type": "main",
            "index": 0
          }
        ]
      ]
    },
    "Filter": {
      "main": [
        [
          {
            "node": "Select rows from a table",
            "type": "main",
            "index": 0
          }
        ]
      ]
    },
    "Select rows from a table": {
      "main": [
        [
          {
            "node": "Filter1",
            "type": "main",
            "index": 0
          }
        ]
      ]
    },
    "Filter1": {
      "main": [
        [
          {
            "node": "Insert rows in a table",
            "type": "main",
            "index": 0
          }
        ]
      ]
    }
  },
  "createdAt": "2025-09-10T15:08:50.441Z",
  "id": "wYmpWFfhOtCztar9",
  "isArchived": false,
  "meta": {
    "templateCredsSetupCompleted": true
  },
  "name": "ParticipantesZoom",
  "nodes": [
    {
      "parameters": {
        "httpMethod": "POST",
        "path": "participanteszoom",
        "options": {}
      },
      "type": "n8n-nodes-base.webhook",
      "typeVersion": 2.1,
      "position": [
        0,
        -16
      ],
      "id": "0419e2d8-3a7d-48ee-9178-0b0d41a62d82",
      "name": "Webhook",
      "webhookId": "adbe6404-9b46-4555-9518-2d8571ec7b8f"
    },
    {
      "parameters": {
        "fieldToSplitOut": "body.zoom_data.participants",
        "options": {}
      },
      "type": "n8n-nodes-base.splitOut",
      "typeVersion": 1,
      "position": [
        224,
        -16
      ],
      "id": "4ae04678-05a6-48f7-8e02-9f52e3f3b227",
      "name": "Split Out"
    },
    {
      "parameters": {
        "operation": "select",
        "schema": {
          "__rl": true,
          "value": "bitrix",
          "mode": "list",
          "cachedResultName": "bitrix"
        },
        "table": {
          "__rl": true,
          "value": "participantes",
          "mode": "list",
          "cachedResultName": "participantes"
        },
        "where": {
          "values": [
            {
              "column": "id",
              "value": "={{ new Date($('Split Out').item.json.join_time).toISOString().split('T')[0] + $('Split Out').item.json.user_email.toLowerCase() }}"
            }
          ]
        },
        "options": {}
      },
      "type": "n8n-nodes-base.postgres",
      "typeVersion": 2.6,
      "position": [
        672,
        -16
      ],
      "id": "ce73fadc-377d-48e7-a3e6-7630591fc218",
      "name": "Select rows from a table",
      "credentials": {
        "postgres": {
          "id": "fuKiWlAN9ojbRM9W",
          "name": "Postgres account"
        }
      }
    },
    {
      "parameters": {
        "conditions": {
          "options": {
            "caseSensitive": true,
            "leftValue": "",
            "typeValidation": "strict",
            "version": 2
          },
          "conditions": [
            {
              "id": "4b0ea8e6-2c88-4b73-8fe1-45d9fec29096",
              "leftValue": "={{ $json.status }}",
              "rightValue": "in_meeting",
              "operator": {
                "type": "string",
                "operation": "equals",
                "name": "filter.operator.equals"
              }
            },
            {
              "id": "96a9a3e3-228e-4bfd-bfbd-9784c24843cc",
              "leftValue": "={{ $json.user_email }}",
              "rightValue": "",
              "operator": {
                "type": "string",
                "operation": "exists",
                "singleValue": true
              }
            }
          ],
          "combinator": "and"
        },
        "options": {}
      },
      "type": "n8n-nodes-base.filter",
      "typeVersion": 2.2,
      "position": [
        448,
        -16
      ],
      "id": "679ac445-a021-4df1-a700-dd803aea8c27",
      "name": "Filter"
    },
    {
      "parameters": {
        "conditions": {
          "options": {
            "caseSensitive": true,
            "leftValue": "",
            "typeValidation": "strict",
            "version": 2
          },
          "conditions": [
            {
              "id": "f60b9b83-19e9-4caf-b26b-7e72f1fc935e",
              "leftValue": "={{ $json.id }}",
              "rightValue": "",
              "operator": {
                "type": "string",
                "operation": "exists",
                "singleValue": true
              }
            }
          ],
          "combinator": "and"
        },
        "options": {}
      },
      "type": "n8n-nodes-base.filter",
      "typeVersion": 2.2,
      "position": [
        896,
        -16
      ],
      "id": "93d088e8-c67a-46f3-a998-c1eb5ae66b89",
      "name": "Filter1"
    },
    {
      "parameters": {
        "schema": {
          "__rl": true,
          "value": "bitrix",
          "mode": "list",
          "cachedResultName": "bitrix"
        },
        "table": {
          "__rl": true,
          "value": "participantes",
          "mode": "list",
          "cachedResultName": "participantes"
        },
        "columns": {
          "mappingMode": "defineBelow",
          "value": {
            "id": "0"
          },
          "matchingColumns": [
            "id"
          ],
          "schema": [
            {
              "id": "fecha",
              "displayName": "fecha",
              "required": false,
              "defaultMatch": false,
              "display": true,
              "type": "dateTime",
              "canBeUsedToMatch": true
            },
            {
              "id": "nombre",
              "displayName": "nombre",
              "required": false,
              "defaultMatch": false,
              "display": true,
              "type": "string",
              "canBeUsedToMatch": true
            },
            {
              "id": "email",
              "displayName": "email",
              "required": false,
              "defaultMatch": false,
              "display": true,
              "type": "string",
              "canBeUsedToMatch": true
            },
            {
              "id": "estanciatotal",
              "displayName": "estanciatotal",
              "required": false,
              "defaultMatch": false,
              "display": true,
              "type": "string",
              "canBeUsedToMatch": true
            },
            {
              "id": "id",
              "displayName": "id",
              "required": true,
              "defaultMatch": true,
              "display": true,
              "type": "string",
              "canBeUsedToMatch": true,
              "removed": false
            },
            {
              "id": "tipo_reunion",
              "displayName": "tipo_reunion",
              "required": false,
              "defaultMatch": false,
              "display": true,
              "type": "string",
              "canBeUsedToMatch": true
            }
          ],
          "attemptToConvertTypes": false,
          "convertFieldsToString": false
        },
        "options": {}
      },
      "type": "n8n-nodes-base.postgres",
      "typeVersion": 2.6,
      "position": [
        1120,
        -16
      ],
      "id": "926e7a5d-1a81-4e9a-8c9b-da3b875923d6",
      "name": "Insert rows in a table",
      "credentials": {
        "postgres": {
          "id": "fuKiWlAN9ojbRM9W",
          "name": "Postgres account"
        }
      }
    }
  ],
  "pinData": {
    "Webhook": [
      {
        "json": {
          "headers": {
            "host": "primary-production-0299.up.railway.app",
            "user-agent": "Make/production",
            "content-length": "757",
            "accept-encoding": "gzip, br, deflate",
            "content-type": "application/json",
            "traceparent": "00-68c207fd0000000054c0c00094fabb50-54c0c00094fabb50-00",
            "tracestate": "dd=t.tid:68c207fd00000000;t.dm:-1;s:0;p:54c0c00094fabb50",
            "x-datadog-parent-id": "6107092203446385488",
            "x-datadog-sampling-priority": "0",
            "x-datadog-tags": "_dd.p.tid=68c207fd00000000",
            "x-datadog-trace-id": "6107092203446385488",
            "x-forwarded-for": "54.161.178.114",
            "x-forwarded-host": "primary-production-0299.up.railway.app",
            "x-forwarded-proto": "https",
            "x-railway-edge": "railway/us-east4-eqdc4a",
            "x-railway-request-id": "hyq1pob6TgemdjipezItjw",
            "x-real-ip": "54.161.178.114",
            "x-request-start": "1757546493508"
          },
          "params": {},
          "query": {},
          "body": {
            "zoom_data": {
              "page_count": 1,
              "page_size": 300,
              "total_records": 2,
              "next_page_token": "",
              "participants": [
                {
                  "id": "UpwoRu5gTPeIr1zl9q1XmQ",
                  "user_id": "16778240",
                  "name": "Proper - Tu mejor (in)versión",
                  "user_email": "info@propinvest.com.pe",
                  "join_time": "2025-09-09T20:40:28Z",
                  "leave_time": "2025-09-09T22:09:00Z",
                  "duration": 5312,
                  "registrant_id": "",
                  "failover": false,
                  "status": "in_meeting",
                  "groupId": "",
                  "internal_user": true
                },
                {
                  "id": "UpwoRu5gTPeIr1zl9q1XmQ",
                  "user_id": "33555456",
                  "name": "Proper - Tu mejor (in)versión",
                  "user_email": "info@propinvest.com.pe",
                  "join_time": "2025-09-09T20:42:55Z",
                  "leave_time": "2025-09-09T22:09:00Z",
                  "duration": 5165,
                  "registrant_id": "",
                  "failover": false,
                  "status": "in_meeting",
                  "groupId": "",
                  "internal_user": true
                }
              ]
            },
            "object_id": "87689245296"
          },
          "webhookUrl": "https://primary-production-0299.up.railway.app/webhook/participanteszoom",
          "executionMode": "production"
        }
      }
    ]
  },
  "settings": {
    "executionOrder": "v1"
  },
  "shared": [
    {
      "createdAt": "2025-09-10T15:08:50.441Z",
      "updatedAt": "2025-09-10T15:08:50.441Z",
      "role": "workflow:owner",
      "workflowId": "wYmpWFfhOtCztar9",
      "projectId": "tpSonpyzopDOYZNA"
    }
  ],
  "staticData": null,
  "tags": [],
  "triggerCount": 1,
  "updatedAt": "2025-09-11T20:56:24.859Z",
  "versionId": "1afb875b-00c8-4317-9e87-c076af13f6f7"
}